py_git/__init__.py
py_git/cli.py
py_git/core/__init__.py
py_git/core/add.py
py_git/core/checkout.py
py_git/core/commit.py
py_git/core/diff.py
py_git/core/init.py
py_git/core/logs.py
py_git/core/status.py
py_git/helpers/__init__.py
py_git/helpers/commit_files.py
py_git/helpers/current_files.py
py_git/helpers/is_a_repos.py
minipygit-0.1.5.dist-info/METADATA
minipygit-0.1.5.dist-info/WHEEL
minipygit-0.1.5.dist-info/entry_points.txt
minipygit-0.1.5.dist-info/top_level.txt
minipygit-0.1.5.dist-info/RECORD
