Metadata-Version: 2.4
Name: minipygit
Version: 0.1.5
Summary: mini version control system written in python
Author-email: romeomanoela <romeomanoela18@gmail.com>
License-Expression: MIT
Classifier: Programming Language :: Python :: 3
Classifier: Operating System :: OS Independent
Classifier: Development Status :: 3 - Alpha
Requires-Python: >=3.12
Requires-Dist: rich>=14.0.0
Provides-Extra: dev
Requires-Dist: black>=25.1.0; extra == "dev"
Requires-Dist: build>=1.2.2.post1; extra == "dev"
Requires-Dist: twine>=6.1.0; extra == "dev"
Requires-Dist: setuptools>=61.0; extra == "dev"
